[
    {
        "stepId": "STEP337",
        "stepName": "Url: WebTours",
        "infFile": "t1.inf",
        "time": 1727551810868
    },
    {
        "stepId": "STEP338",
        "stepName": "Submit Form: login.pl",
        "infFile": "t2.inf",
        "time": 1727551811164
    },
    {
        "stepId": "STEP339",
        "stepName": "Image: Search Flights Button",
        "infFile": "t3.inf",
        "time": 1727551811459
    },
    {
        "stepId": "STEP340",
        "stepName": "Submit Form: reservations.pl",
        "infFile": "t4.inf",
        "time": 1727551811731
    },
    {
        "stepId": "STEP341",
        "stepName": "Submit Form: reservations.pl_2",
        "infFile": "t5.inf",
        "time": 1727551811968
    },
    {
        "stepId": "STEP342",
        "stepName": "Submit Form: reservations.pl_3",
        "infFile": "t6.inf",
        "time": 1727551812189
    }
]