[
    {
        "stepId": "STEP355",
        "stepName": "Url: WebTours",
        "infFile": "t1.inf",
        "time": 1727551815885
    },
    {
        "stepId": "STEP356",
        "stepName": "Submit Form: login.pl",
        "infFile": "t2.inf",
        "time": 1727551816194
    },
    {
        "stepId": "STEP357",
        "stepName": "Image: Search Flights Button",
        "infFile": "t3.inf",
        "time": 1727551816505
    },
    {
        "stepId": "STEP358",
        "stepName": "Submit Form: reservations.pl",
        "infFile": "t4.inf",
        "time": 1727551816804
    },
    {
        "stepId": "STEP359",
        "stepName": "Submit Form: reservations.pl_2",
        "infFile": "t5.inf",
        "time": 1727551817047
    },
    {
        "stepId": "STEP360",
        "stepName": "Submit Form: reservations.pl_3",
        "infFile": "t6.inf",
        "time": 1727551817269
    }
]